calcflow/__init__.py
calcflow/slurm.py
calcflow/utils.py
calcflow/basis/__init__.py
calcflow/basis/loader.py
calcflow/basis/models.py
calcflow/common/__init__.py
calcflow/common/exceptions.py
calcflow/common/input.py
calcflow/common/patterns.py
calcflow/common/results.py
calcflow/common/types.py
calcflow/constants/__init__.py
calcflow/constants/ptable.py
calcflow/geometry/__init__.py
calcflow/geometry/static.py
calcflow/geometry/trajectory.py
calcflow/io/__init__.py
calcflow/io/core.py
calcflow/io/state.py
calcflow/io/orca/__init__.py
calcflow/io/orca/builder.py
calcflow/io/orca/parser.py
calcflow/io/orca/blocks/__init__.py
calcflow/io/orca/blocks/charges.py
calcflow/io/orca/blocks/dipole.py
calcflow/io/orca/blocks/dispersion.py
calcflow/io/orca/blocks/finalization.py
calcflow/io/orca/blocks/geometry.py
calcflow/io/orca/blocks/orbitals.py
calcflow/io/orca/blocks/scf.py
calcflow/io/orca/blocks/timing.py
calcflow/io/qchem/__init__.py
calcflow/io/qchem/builder.py
calcflow/io/qchem/parser.py
calcflow/io/qchem/blocks/charges.py
calcflow/io/qchem/blocks/finalization.py
calcflow/io/qchem/blocks/geometry.py
calcflow/io/qchem/blocks/metadata.py
calcflow/io/qchem/blocks/multipole.py
calcflow/io/qchem/blocks/orbitals.py
calcflow/io/qchem/blocks/patterns.py
calcflow/io/qchem/blocks/scf.py
calcflow/io/qchem/blocks/timing.py
calcflow/io/qchem/blocks/tddft/__init__.py
calcflow/io/qchem/blocks/tddft/excitations.py
calcflow/io/qchem/blocks/tddft/gs_ref.py
calcflow/io/qchem/blocks/tddft/nto.py
calcflow/io/qchem/blocks/tddft/trans_dm.py
calcflow/io/qchem/blocks/tddft/unrel_dm.py
calcflow/visualize/__init__.py
calcflow/visualize/opt.py
calcflow/visualize/scf.py
calcflow-0.3.0.dist-info/licenses/LICENSE
calcflow-0.3.0.dist-info/METADATA
calcflow-0.3.0.dist-info/WHEEL
calcflow-0.3.0.dist-info/top_level.txt
calcflow-0.3.0.dist-info/RECORD
