Metadata-Version: 2.4
Name: calcflow
Version: 0.3.0
Summary: Add your description here
Author-email: Anton Morgunov <anton@ischemist.com>
License: MIT
Project-URL: Homepage, https://github.com/ischemist/project-prometheus
Project-URL: Issues, https://github.com/ischemist/project-prometheus/issues
Classifier: Programming Language :: Python :: 3
Classifier: License :: OSI Approved :: MIT License
Classifier: Operating System :: OS Independent
Classifier: Intended Audience :: Science/Research
Classifier: Topic :: Scientific/Engineering :: Chemistry
Classifier: Typing :: Typed
Requires-Python: >=3.13
License-File: LICENSE
Dynamic: license-file
